suriyaunittestdf.py
suriyaunittestdf-0.0.1.dist-info/LICENCE.txt
suriyaunittestdf-0.0.1.dist-info/METADATA
suriyaunittestdf-0.0.1.dist-info/WHEEL
suriyaunittestdf-0.0.1.dist-info/top_level.txt
suriyaunittestdf-0.0.1.dist-info/RECORD
