Metadata-Version: 2.1
Name: suriyaunittestdf
Version: 0.0.1
Summary: suriyaunittestdf!
Home-page: UNKNOWN
License: UNKNOWN
Platform: UNKNOWN
